alu.sv
// alu.sv
// Tanish Gheewala - March 2026
// Parametric Arithmetic Logic Unit (ALU) at the RTL Level

`timescale 1ns/1ps

// Module Header
module alu #(
    parameter int WIDTH = 8,         // Operand Width (Default: 8)
    parameter int OPW   = 4          // Opcode Width (Default: 4)
) ( // Input & Output Ports
    input  logic [WIDTH-1:0]         A,
    input  logic [WIDTH-1:0]         B,
    input  logic [OPW-1:0]           op,
    input  logic                     signed_mode,

    output logic [(2*WIDTH)-1:0]     Y,
    output logic                     OVF
);

// 4-bit Opcode Table
// Logic Operations
localparam logic [OPW-1:0] OP_AND = 4'b0000;
localparam logic [OPW-1:0] OP_OR  = 4'b0001;
localparam logic [OPW-1:0] OP_XOR = 4'b0010;
localparam logic [OPW-1:0] OP_NOT = 4'b0011;
// Arithmetic Operations
localparam logic [OPW-1:0] OP_ADD = 4'b0100;
localparam logic [OPW-1:0] OP_SUB = 4'b0101;
localparam logic [OPW-1:0] OP_INC = 4'b0110;
localparam logic [OPW-1:0] OP_DEC = 4'b0111;
localparam logic [OPW-1:0] OP_MUL = 4'b1000;
// Shift Operations
localparam logic [OPW-1:0] OP_SLL = 4'b1001;
localparam logic [OPW-1:0] OP_SRL = 4'b1010;
localparam logic [OPW-1:0] OP_SRA = 4'b1011;
// Comparison Operations
localparam logic [OPW-1:0] OP_EQ  = 4'b1100;
localparam logic [OPW-1:0] OP_GT  = 4'b1101;
localparam logic [OPW-1:0] OP_GE  = 4'b1110;
localparam logic [OPW-1:0] OP_SLT = 4'b1111;

// Helper for Signed/Unsigned Views
logic signed [WIDTH-1:0] A_s;
logic signed [WIDTH-1:0] B_s;
logic [WIDTH-1:0]        A_u;
logic [WIDTH-1:0]        B_u;

// Shift Amount Width Calculation
localparam int SHAMT_W = (WIDTH <= 1) ? 1 : $clog2(WIDTH); // ceiling(log2(WIDTH))
logic [SHAMT_W-1:0] shamt;

// Treat as Signed/Unsigned
assign A_s  = A;
assign B_s  = B;
assign A_u  = A;
assign B_u  = B;
assign shamt = B[SHAMT_W-1:0];

// Combinational ALU Logic
always_comb begin

    // Default Outputs
    Y   = '0;
    OVF = 1'b0;
    
    // Note: Upgrade to Case Statement instead of If

    // Logic Operations
    if (op == OP_AND) begin // AND: A & B
        Y = { {WIDTH{1'b0}}, (A & B) };

    end else if (op == OP_OR) begin // OR: A | B
        Y = { {WIDTH{1'b0}}, (A | B) };

    end else if (op == OP_XOR) begin // XOR: A ^ B
        Y = { {WIDTH{1'b0}}, (A ^ B) };

    end else if (op == OP_NOT) begin // NOT: ~A (B ignored)
        Y = { {WIDTH{1'b0}}, (~A) };

    // Arithmetic Operations
    end else if (op == OP_ADD) begin // ADD: A + B
        logic [WIDTH-1:0] r;
        logic [WIDTH:0]   ext;
        r   = A + B;
        ext = {1'b0, A} + {1'b0, B};
        if (signed_mode) begin
            Y   = { {WIDTH{r[WIDTH-1]}}, r };
            OVF = (A_s[WIDTH-1] == B_s[WIDTH-1]) && (r[WIDTH-1] != A_s[WIDTH-1]);
        end else begin
            Y   = { {WIDTH{1'b0}}, r };
            OVF = ext[WIDTH];
        end

    end else if (op == OP_SUB) begin // SUB: A - B
        logic [WIDTH-1:0] r;
        logic             borrow;
        r      = A - B;
        borrow = (A_u < B_u);
        if (signed_mode) begin
            Y   = { {WIDTH{r[WIDTH-1]}}, r };
            OVF = (A_s[WIDTH-1] != B_s[WIDTH-1]) && (r[WIDTH-1] != A_s[WIDTH-1]);
        end else begin
            Y   = { {WIDTH{1'b0}}, r };
            OVF = borrow;
        end

    end else if (op == OP_INC) begin // INC: A + 1
        logic [WIDTH-1:0] r;
        logic [WIDTH:0]   ext;
        r   = A + 1'b1;
        ext = {1'b0, A} + {{WIDTH{1'b0}}, 1'b1};
        if (signed_mode) begin
            Y   = { {WIDTH{r[WIDTH-1]}}, r };
            OVF = (A_s[WIDTH-1] == 1'b0) && (r[WIDTH-1] == 1'b1);
        end else begin
            Y   = { {WIDTH{1'b0}}, r };
            OVF = ext[WIDTH];
        end

    end else if (op == OP_DEC) begin // DEC: A - 1
        logic [WIDTH-1:0] r;
        logic             borrow;
        r      = A - 1'b1;
        borrow = (A_u < 1);
        if (signed_mode) begin
            Y   = { {WIDTH{r[WIDTH-1]}}, r };
            OVF = (A_s[WIDTH-1] == 1'b1) && (r[WIDTH-1] == 1'b0);
        end else begin
            Y   = { {WIDTH{1'b0}}, r };
            OVF = borrow;
        end

    end else if (op == OP_MUL) begin // MUL: A * B
        if (signed_mode) begin
            Y = $signed(A_s) * $signed(B_s);
        end else begin
            Y = A_u * B_u;
        end

    // Shift Operations
    // Shamt = Lower Bits of B
    end else if (op == OP_SLL) begin // SLL: A << shamt
        Y = { {WIDTH{1'b0}}, (A << shamt) };

    end else if (op == OP_SRL) begin // SRL: A >> shamt
        Y = { {WIDTH{1'b0}}, (A >> shamt) };

    end else if (op == OP_SRA) begin // SRA: A >>> shamt
        Y = { {WIDTH{1'b0}}, (A_s >>> shamt) };
        
    // Comparison Operations
    // EQ = Equal, GT = Greater Than, GE = Greater or Equal, SLT = Set on Less Than
    end else if (op == OP_EQ) begin // EQ: A == B
        Y = (A == B) ? {{(2*WIDTH-1){1'b0}}, 1'b1} : '0;

    end else if (op == OP_GT) begin // GT: A > B
        if (signed_mode) Y = (A_s > B_s) ? {{(2*WIDTH-1){1'b0}}, 1'b1} : '0;
        else             Y = (A_u > B_u) ? {{(2*WIDTH-1){1'b0}}, 1'b1} : '0;

    end else if (op == OP_GE) begin // GE: A >= B
        if (signed_mode) Y = (A_s >= B_s) ? {{(2*WIDTH-1){1'b0}}, 1'b1} : '0;
        else             Y = (A_u >= B_u) ? {{(2*WIDTH-1){1'b0}}, 1'b1} : '0;

    end else if (op == OP_SLT) begin // SLT: A < B
        if (signed_mode) begin
            Y = (A_s < B_s) ? {{(2*WIDTH-1){1'b0}}, 1'b1} : '0;
        end else begin
            Y = (A_u < B_u) ? {{(2*WIDTH-1){1'b0}}, 1'b1} : '0;
        end

    end else begin
    end

end
endmodule

tb_alu.sv
// tb_alu.sv
// Tanish Gheewala - March 2026
// Testbench for the Parametric Arithmetic Logic Unit (ALU) at the RTL Level

`timescale 1ns/1ps

// Module Header
module tb_alu;
    // Must match alu.sv parameters
    localparam int WIDTH = 8;
    localparam int OPW   = 4;

    // DUT inputs
    logic [WIDTH-1:0] A;
    logic [WIDTH-1:0] B;
    logic [OPW-1:0]   op;
    logic             signed_mode;

    // DUT outputs
    logic [(2*WIDTH)-1:0] Y;
    logic                 OVF;

    // DUT Instantiation
    alu #(
        .WIDTH(WIDTH),
        .OPW(OPW)
    ) dut (
        .A(A),
        .B(B),
        .op(op),
        .signed_mode(signed_mode),
        .Y(Y),
        .OVF(OVF)
    );

    // Waveform Dump (for GTKWave)
    initial begin
        $dumpfile("tb_alu.vcd");
        $dumpvars(0, tb_alu);
    end

    // 4-bit Opcode Table (must match alu.sv)
    // Logic Operations
    localparam logic [OPW-1:0] OP_AND = 4'b0000;
    localparam logic [OPW-1:0] OP_OR  = 4'b0001;
    localparam logic [OPW-1:0] OP_XOR = 4'b0010;
    localparam logic [OPW-1:0] OP_NOT = 4'b0011;
    // Arithmetic Operations
    localparam logic [OPW-1:0] OP_ADD = 4'b0100;
    localparam logic [OPW-1:0] OP_SUB = 4'b0101;
    localparam logic [OPW-1:0] OP_INC = 4'b0110;
    localparam logic [OPW-1:0] OP_DEC = 4'b0111;
    localparam logic [OPW-1:0] OP_MUL = 4'b1000;
    // Shift Operations
    localparam logic [OPW-1:0] OP_SLL = 4'b1001;
    localparam logic [OPW-1:0] OP_SRL = 4'b1010;
    localparam logic [OPW-1:0] OP_SRA = 4'b1011;
    // Comparison Operations
    localparam logic [OPW-1:0] OP_EQ  = 4'b1100;
    localparam logic [OPW-1:0] OP_GT  = 4'b1101;
    localparam logic [OPW-1:0] OP_GE  = 4'b1110;
    localparam logic [OPW-1:0] OP_SLT = 4'b1111;

    // Test
    int tests  = 0;
    int errors = 0;

    // Outputs a pass/fail message and increments test/error counters
    task automatic check(
        input logic [WIDTH-1:0]         tA,
        input logic [WIDTH-1:0]         tB,
        input logic [OPW-1:0]           tOP,
        input logic                     tSM,
        input logic [(2*WIDTH)-1:0]     expY,
        input logic                     expOVF,
        input string                    name
    );
    begin
        A = tA;
        B = tB;
        op = tOP;
        signed_mode = tSM;
        #1;
        tests++;
        if ((Y !== expY) || (OVF !== expOVF)) begin
            errors++;
            $display("FAIL: %s | A=%h B=%h op=%b sm=%0d | Y=%h (exp %h) OVF=%0d (exp %0d)",
                     name, A, B, op, signed_mode, Y, expY, OVF, expOVF);
        end else begin
            $display("PASS: %s", name);
        end
    end
    endtask

    initial begin
        A = '0;
        B = '0;
        op = '0;
        signed_mode = 1'b0;
        #1;

        $display("tb_alu start");

        // Required Tests
        check(8'h0F, 8'hF0, OP_AND, 1'b0, 16'h0000, 1'b0, "AND: 0F & F0");
        check(8'h0F, 8'hF0, OP_OR , 1'b0, 16'h00FF, 1'b0, "OR : 0F | F0");
        check(8'hAA, 8'h0F, OP_XOR, 1'b0, 16'h00A5, 1'b0, "XOR: AA ^ 0F");
        check(8'h00, 8'h00, OP_NOT, 1'b0, 16'h00FF, 1'b0, "NOT: ~00");
        check(8'h7F, 8'h01, OP_ADD, 1'b1, 16'hFF80, 1'b1, "ADD signed ovf: 7F + 01");
        check(8'h80, 8'h01, OP_SUB, 1'b1, 16'h007F, 1'b1, "SUB signed ovf: 80 - 01");
        check(8'hFF, 8'h01, OP_ADD, 1'b0, 16'h0000, 1'b1, "ADD unsigned wrap: FF + 01");
        check(8'hFF, 8'h01, OP_SLT, 1'b1, 16'h0001, 1'b0, "SLT signed: FF < 01");
        check(8'hFF, 8'h01, OP_SLT, 1'b0, 16'h0000, 1'b0, "SLT unsigned: FF < 01");
        check(8'hFF, 8'h02, OP_MUL, 1'b1, 16'hFFFE, 1'b0, "MUL signed: FF * 02");
        check(8'hFF, 8'h02, OP_MUL, 1'b0, 16'h01FE, 1'b0, "MUL unsigned: FF * 02");
        check(8'hF0, 8'h02, OP_SRA, 1'b0, 16'h00FC, 1'b0, "SRA: F0 >>> 2");
        check(8'h01, 8'h07, OP_SLL, 1'b0, 16'h0080, 1'b0, "SLL max: 01 << 7");
        check(8'h80, 8'h07, OP_SRL, 1'b0, 16'h0001, 1'b0, "SRL max: 80 >> 7");
        check(8'h80, 8'h07, OP_SRA, 1'b0, 16'h00FF, 1'b0, "SRA max: 80 >>> 7");

        $display("tb_alu done | tests=%0d errors=%0d", tests, errors);
        $finish;
    end

endmodule

tb_alu.vcd
$date
	Wed Mar 04 13:46:13 2026
$end
$version
	Icarus Verilog
$end
$timescale
	1ps
$end
$scope module tb_alu $end
$var wire 16 ! Y [15:0] $end
$var wire 1 " OVF $end
$var parameter 32 # OPW $end
$var parameter 4 $ OP_ADD $end
$var parameter 4 % OP_AND $end
$var parameter 4 & OP_DEC $end
$var parameter 4 ' OP_EQ $end
$var parameter 4 ( OP_GE $end
$var parameter 4 ) OP_GT $end
$var parameter 4 * OP_INC $end
$var parameter 4 + OP_MUL $end
$var parameter 4 , OP_NOT $end
$var parameter 4 - OP_OR $end
$var parameter 4 . OP_SLL $end
$var parameter 4 / OP_SLT $end
$var parameter 4 0 OP_SRA $end
$var parameter 4 1 OP_SRL $end
$var parameter 4 2 OP_SUB $end
$var parameter 4 3 OP_XOR $end
$var parameter 32 4 WIDTH $end
$var reg 8 5 A [7:0] $end
$var reg 8 6 B [7:0] $end
$var reg 4 7 op [3:0] $end
$var reg 1 8 signed_mode $end
$var integer 32 9 errors [31:0] $end
$var integer 32 : tests [31:0] $end
$scope module dut $end
$var wire 8 ; A [7:0] $end
$var wire 8 < A_s [7:0] $end
$var wire 8 = A_u [7:0] $end
$var wire 8 > B [7:0] $end
$var wire 8 ? B_s [7:0] $end
$var wire 8 @ B_u [7:0] $end
$var wire 4 A op [3:0] $end
$var wire 1 8 signed_mode $end
$var wire 3 B shamt [2:0] $end
$var parameter 32 C OPW $end
$var parameter 4 D OP_ADD $end
$var parameter 4 E OP_AND $end
$var parameter 4 F OP_DEC $end
$var parameter 4 G OP_EQ $end
$var parameter 4 H OP_GE $end
$var parameter 4 I OP_GT $end
$var parameter 4 J OP_INC $end
$var parameter 4 K OP_MUL $end
$var parameter 4 L OP_NOT $end
$var parameter 4 M OP_OR $end
$var parameter 4 N OP_SLL $end
$var parameter 4 O OP_SLT $end
$var parameter 4 P OP_SRA $end
$var parameter 4 Q OP_SRL $end
$var parameter 4 R OP_SUB $end
$var parameter 4 S OP_XOR $end
$var parameter 32 T SHAMT_W $end
$var parameter 32 U WIDTH $end
$var reg 1 " OVF $end
$var reg 16 V Y [15:0] $end
$scope begin $unm_blk_11 $end
$var reg 9 W ext [8:0] $end
$var reg 8 X r [7:0] $end
$upscope $end
$scope begin $unm_blk_14 $end
$var reg 1 Y borrow $end
$var reg 8 Z r [7:0] $end
$upscope $end
$scope begin $unm_blk_17 $end
$var reg 9 [ ext [8:0] $end
$var reg 8 \ r [7:0] $end
$upscope $end
$scope begin $unm_blk_20 $end
$var reg 1 ] borrow $end
$var reg 8 ^ r [7:0] $end
$upscope $end
$upscope $end
$scope task check $end
$upscope $end
$upscope $end
$enddefinitions $end
$comment Show the parameter values. $end
$dumpall
b1000 U
b11 T
b10 S
b101 R
b1010 Q
b1011 P
b1111 O
b1001 N
b1 M
b11 L
b1000 K
b110 J
b1101 I
b1110 H
b1100 G
b111 F
b0 E
b100 D
b100 C
b1000 4
b10 3
b101 2
b1010 1
b1011 0
b1111 /
b1001 .
b1 -
b11 ,
b1000 +
b110 *
b1101 )
b1110 (
b1100 '
b111 &
b0 %
b100 $
b100 #
$end
#0
$dumpvars
bx ^
x]
bx \
bx [
bx Z
xY
bx X
bx W
b0 V
b0 B
b0 A
b0 @
b0 ?
b0 >
b0 =
b0 <
b0 ;
b0 :
b0 9
08
b0 7
b0 6
b0 5
0"
b0 !
$end
#1000
b11110000 ?
b11110000 @
b11110000 6
b11110000 >
b1111 <
b1111 =
b1111 5
b1111 ;
#2000
b11111111 !
b11111111 V
b1 7
b1 A
b1 :
#3000
b111 B
b10100101 !
b10100101 V
b10 7
b10 A
b1111 ?
b1111 @
b1111 6
b1111 >
b10101010 <
b10101010 =
b10101010 5
b10101010 ;
b10 :
#4000
b0 B
b11111111 !
b11111111 V
b11 7
b11 A
b0 ?
b0 @
b0 6
b0 >
b0 <
b0 =
b0 5
b0 ;
b11 :
#5000
b1 B
1"
b10000000 W
b10000000 X
b1111111110000000 !
b1111111110000000 V
18
b100 7
b100 A
b1 ?
b1 @
b1 6
b1 >
b1111111 <
b1111111 =
b1111111 5
b1111111 ;
b100 :
#6000
0Y
b1111111 Z
1"
b1111111 !
b1111111 V
b101 7
b101 A
b10000000 <
b10000000 =
b10000000 5
b10000000 ;
b101 :
#7000
b100000000 W
b0 X
1"
b0 !
b0 V
08
b100 7
b100 A
b11111111 <
b11111111 =
b11111111 5
b11111111 ;
b110 :
#8000
b1 !
b1 V
0"
18
b1111 7
b1111 A
b111 :
#9000
b0 !
b0 V
08
b1000 :
#10000
b1111111111111110 !
b1111111111111110 V
b10 B
18
b1000 7
b1000 A
b10 ?
b10 @
b10 6
b10 >
b1001 :
#11000
b111111110 !
b111111110 V
08
b1010 :
#12000
b11111100 !
b11111100 V
b1011 7
b1011 A
b11110000 <
b11110000 =
b11110000 5
b11110000 ;
b1011 :
#13000
b111 B
b10000000 !
b10000000 V
b1001 7
b1001 A
b111 ?
b111 @
b111 6
b111 >
b1 <
b1 =
b1 5
b1 ;
b1100 :
#14000
b1 !
b1 V
b1010 7
b1010 A
b10000000 <
b10000000 =
b10000000 5
b10000000 ;
b1101 :
#15000
b11111111 !
b11111111 V
b1011 7
b1011 A
b1110 :
#16000
b1111 :
