tb_alu.v
`timescale 1ns/1ps

module tb;
  reg clk;
  reg rst;
  reg toggle;
  reg [3:0] count;

  initial begin
    clk = 0;
    forever #5 clk = ~clk;
  end

  initial begin
    rst    = 1;
    toggle = 0;
    count  = 0;

    $dumpfile("wave.vcd");
    $dumpvars(0, tb);

    #12 rst = 0;

    #100 $finish;
  end

  always @(posedge clk) begin
    if (rst) begin
      count  <= 0;
      toggle <= 0;
    end else begin
      count  <= count + 1;
      toggle <= ~toggle;
    end
  end

endmodule

wave.vcd
$date
	Fri Feb 27 19:14:04 2026
$end
$version
	Icarus Verilog
$end
$timescale
	1ps
$end
$scope module tb $end
$var reg 1 ! clk $end
$var reg 4 " count [3:0] $end
$var reg 1 # rst $end
$var reg 1 $ toggle $end
$upscope $end
$enddefinitions $end
$comment Show the parameter values. $end
$dumpall
$end
#0
$dumpvars
0$
1#
b0 "
0!
$end
#5000
1!
#10000
0!
#12000
0#
#15000
1$
b1 "
1!
#20000
0!
#25000
0$
b10 "
1!
#30000
0!
#35000
1$
b11 "
1!
#40000
0!
#45000
0$
b100 "
1!
#50000
0!
#55000
1$
b101 "
1!
#60000
0!
#65000
0$
b110 "
1!
#70000
0!
#75000
1$
b111 "
1!
#80000
0!
#85000
0$
b1000 "
1!
#90000
0!
#95000
1$
b1001 "
1!
#100000
0!
#105000
0$
b1010 "
1!
